{"product_type": "vivo X5L 16GB 移动版4G手机(白色)", "url": "http://product.pcpop.com/000592874/Comment.html", "series": "X", "integration_valuation_score": "3分", "publish_date": "2014-12-26 09:14:57", "evaluation": "优点： 玩游戏快，外观设计好 不足： 像素不好，电池不够 总结： 各方面都很一般。没我想象的那么好", "product_name": "vivo"}
{"product_type": "vivo X3L 16GB 移动版4G手机(极光白)", "url": "http://product.pcpop.com/000571709/Comment.html", "series": "X", "integration_valuation_score": "4分", "publish_date": "2014-04-19 21:29:51", "evaluation": "优点： 超薄，有手感。音质非常好 不足： 联发科的处理器，运行游戏不够流畅 总结： 具体的看个人喜好了，认为值得人自然就觉得好，至于那些觉得不好的人也有自己的道理", "product_name": "vivo"}
{"product_type": "vivo X3L 16GB 移动版4G手机(极光白)", "url": "http://product.pcpop.com/000571709/Comment.html", "series": "X", "integration_valuation_score": "1分", "publish_date": "2014-04-05 16:41:48", "evaluation": "不足： 玩游戏卡，经常死机，手机屏幕质量非常差，从床上掉地下，里外屏幕全碎了，怀疑是翻板机。 总结： 总之就是差，以后再也不会买vivo这种手机了。", "product_name": "vivo"}
{"product_type": "vivo X3L 16GB 移动版4G手机(极光白)", "url": "http://product.pcpop.com/000571709/Comment.html", "series": "X", "integration_valuation_score": "4分", "publish_date": "2014-03-14 17:58:46", "evaluation": "优点： 外观好看，很薄 不足： 没有移动3G版本的 总结： 要是有移动版本的就好了", "product_name": "vivo"}
{"product_type": "vivo X3L 16GB 移动版4G手机(极光白)", "url": "http://product.pcpop.com/000571709/Comment.html", "series": "X", "integration_valuation_score": "4分", "publish_date": "2014-02-26 19:47:41", "evaluation": "优点： 机身薄，外观美，音色也可以 不足： 有时候会死机，且不能去电板 总结： 总体还可以。。。。。。", "product_name": "vivo"}
